drb/metadata/__init__.py
drb/metadata/_version.py
drb/metadata/core.py
drb/metadata/schema.yml
drb_metadata-1.3.2.dist-info/LICENCE.txt
drb_metadata-1.3.2.dist-info/METADATA
drb_metadata-1.3.2.dist-info/WHEEL
drb_metadata-1.3.2.dist-info/entry_points.txt
drb_metadata-1.3.2.dist-info/top_level.txt
drb_metadata-1.3.2.dist-info/RECORD
