Metadata-Version: 2.1
Name: drb-metadata
Version: 1.3.2
Summary: DRB Metadata Extractor
Author: GAEL Systems
Author-email: drb-python@gael.fr
License: LGPLv3
Classifier: Programming Language :: Python :: 3.8
Classifier: Environment :: Plugins
Classifier: License :: OSI Approved :: GNU Lesser General Public License v3 (LGPLv3)
Requires-Python: >=3.8
License-File: LICENCE.txt
Requires-Dist: drb ~=2.2.0
Requires-Dist: drb-xquery ~=1.3.0
Requires-Dist: drb-extractor ~=1.2.0
